MANIFEST.in
README.md
setup.py
averaged_perceptron/__init__.py
averaged_perceptron.egg-info/PKG-INFO
averaged_perceptron.egg-info/SOURCES.txt
averaged_perceptron.egg-info/dependency_links.txt
averaged_perceptron.egg-info/requires.txt
averaged_perceptron.egg-info/top_level.txt