Metadata-Version: 2.1
Name: averaged-perceptron
Version: 0.0.0
Summary: Averaged Perceptron
Home-page: https://github.com/blester125/averaged_perceptron
Author: blester125
Author-email: blester125@gmail.com
License: MIT
Download-URL: https://github.com/blester125/averaged_perceptron/archive/0.0.0.tar.gz
Platform: UNKNOWN
Classifier: Topic :: Scientific/Engineering
Classifier: Intended Audience :: Developers
Classifier: Development Status :: 3 - Alpha
Classifier: Natural Language :: English
Classifier: Programming Language :: Python :: 3 :: Only
Classifier: License :: OSI Approved :: MIT License
Classifier: Environment :: Console
Classifier: Intended Audience :: Science/Research
Requires-Python: >=3.6
Provides-Extra: test
